Metadata-Version: 1.1
Name: libscrna
Version: 0.3.0
Summary: A library for dealing with single cell RNA-seq data.
Home-page: https://github.com/antonybholmes/libscrna
Author: Antony B Holmes
Author-email: antony.b.holmes@gmail.com
License: UNKNOWN
Platform: UNKNOWN
Classifier: Programming Language :: Python :: 3
Classifier: License :: OSI Approved :: MIT License
Classifier: Operating System :: OS Independent
